requirements.txt
pytigon_gui/__init__.py
pytigon_gui/pytigon.py
pytigon_gui/wxauto.py
pytigon_gui/guictrl/__init__.py
pytigon_gui/guictrl/basectrl.py
pytigon_gui/guictrl/ctrl.py
pytigon_gui/guictrl/tag.py
pytigon_gui/guictrl/button/__init__.py
pytigon_gui/guictrl/button/toolbarbutton.py
pytigon_gui/guictrl/grid/__init__.py
pytigon_gui/guictrl/grid/grid.py
pytigon_gui/guictrl/grid/gridpanel.py
pytigon_gui/guictrl/grid/gridtable_base.py
pytigon_gui/guictrl/grid/gridtable_from_html_table.py
pytigon_gui/guictrl/grid/gridtable_from_proxy.py
pytigon_gui/guictrl/grid/popupcelleditors.py
pytigon_gui/guictrl/grid/renderers.py
pytigon_gui/guictrl/grid/tabproxy.py
pytigon_gui/guictrl/popup/__init__.py
pytigon_gui/guictrl/popup/popuphtml.py
pytigon_gui/guictrl/popup/select2.py
pytigon_gui/guiframe/__init__.py
pytigon_gui/guiframe/appframe.py
pytigon_gui/guiframe/baseframe.py
pytigon_gui/guiframe/browserframe.py
pytigon_gui/guiframe/form.py
pytigon_gui/guiframe/manager.py
pytigon_gui/guiframe/notebook.py
pytigon_gui/guiframe/notebookpage.py
pytigon_gui/guiframe/page.py
pytigon_gui/guilib/__init__.py
pytigon_gui/guilib/events.py
pytigon_gui/guilib/httperror.py
pytigon_gui/guilib/image.py
pytigon_gui/guilib/logindialog.py
pytigon_gui/guilib/pytigon_install.py
pytigon_gui/guilib/signal.py
pytigon_gui/guilib/threadwindow.py
pytigon_gui/guilib/tools.py
pytigon_gui/guilib/websocket.py
pytigon_gui/toolbar/__init__.py
pytigon_gui/toolbar/basetoolbar.py
pytigon_gui/toolbar/generictoolbar.py
pytigon_gui/toolbar/menubar.py
pytigon_gui/toolbar/moderntoolbar.py
pytigon_gui/toolbar/standardtoolbar.py
pytigon_gui/toolbar/standardtoolbarbuttons.py
pytigon_gui/toolbar/treetoolbar.py
pytigon_gui-0.250514.dist-info/licenses/LICENSE
pytigon_gui-0.250514.dist-info/METADATA
pytigon_gui-0.250514.dist-info/WHEEL
pytigon_gui-0.250514.dist-info/entry_points.txt
pytigon_gui-0.250514.dist-info/top_level.txt
pytigon_gui-0.250514.dist-info/RECORD
