Metadata-Version: 2.4
Name: pytigon-gui
Version: 0.250514
Summary: Pytigon GUI
Author: Sławomir Chołaj
Author-email: slawomir.cholaj@gmail.com
License: LGPLv3
Classifier: Development Status :: 3 - Alpha
Classifier: Environment :: Web Environment
Classifier: Intended Audience :: Developers
Classifier: License :: OSI Approved :: GNU Lesser General Public License v3 (LGPLv3)
Classifier: Operating System :: OS Independent
Classifier: Programming Language :: Python
Classifier: Programming Language :: Python :: 3.8
Classifier: Programming Language :: Python :: 3.9
Classifier: Programming Language :: Python :: 3.10
Classifier: Programming Language :: Python :: 3.11
Classifier: Programming Language :: Python :: 3.12
Classifier: Programming Language :: Python :: 3.13
Classifier: Topic :: Internet :: WWW/HTTP :: Dynamic Content
Classifier: Topic :: Internet :: WWW/HTTP :: WSGI :: Application
Classifier: Topic :: Software Development :: Libraries :: Application Frameworks
Classifier: Topic :: Software Development :: Libraries :: Python Modules
License-File: LICENSE
Requires-Dist: pytigon-batteries[all]
Requires-Dist: wxpython
Requires-Dist: wxasync
Requires-Dist: PyDispatcher
Requires-Dist: pyshortcuts
Requires-Dist: libsass
Requires-Dist: black
Requires-Dist: pytest
Requires-Dist: pytest-django
Dynamic: author
Dynamic: author-email
Dynamic: classifier
Dynamic: license
Dynamic: license-file
Dynamic: requires-dist
Dynamic: summary
